esanalyzer.py
esanalyzer-1.2.0.dist-info/LICENSE
esanalyzer-1.2.0.dist-info/METADATA
esanalyzer-1.2.0.dist-info/WHEEL
esanalyzer-1.2.0.dist-info/top_level.txt
esanalyzer-1.2.0.dist-info/RECORD
