Metadata-Version: 2.2
Name: esanalyzer
Version: 1.2.0
Summary: Emotion("fear", "anger", "surprise", "sadness", "disgust", "joy") and Sentiment("Positive","Negative","Neutral") Analysis
Home-page: https://github.com/ajaysingh111444/python/tree/esanalyzer/esanalyzer/version/1.2.0
Author: Ajay Singh Rajput
Requires-Python: >=3.12.3
License-File: LICENSE
Requires-Dist: nrclex==3.0.0
Requires-Dist: datasets==2.16.1
Requires-Dist: scikit-learn==1.3.2
Requires-Dist: pandas==2.1.4
Requires-Dist: numpy==1.26.3
Requires-Dist: googletrans==4.0.0-rc1
Requires-Dist: transformers==4.36.2
Requires-Dist: nltk==3.8.1
Requires-Dist: torch==2.3.0
Requires-Dist: torchvision==0.18.0
Requires-Dist: torchaudio==2.3.0
Requires-Dist: tensorflow==2.16.1
Requires-Dist: flax==0.8.3
Requires-Dist: textblob==0.18.0.post0
Requires-Dist: emoji==2.14.0
Dynamic: author
Dynamic: description
Dynamic: description-content-type
Dynamic: home-page
Dynamic: requires-dist
Dynamic: requires-python
Dynamic: summary
